numfy/__init__.py
numfy/cgan.txt
numfy/diffusion.txt
numfy/face.txt
numfy/image.txt
numfy/mod1.txt
numfy/rcnn.txt
numfy/rcnnc.txt
numfy/stable.txt
numfy/vae.txt
numfy/yolo.txt
numfy/yoloc.txt
numfy-1.0.dist-info/METADATA
numfy-1.0.dist-info/WHEEL
numfy-1.0.dist-info/top_level.txt
numfy-1.0.dist-info/RECORD
