Metadata-Version: 2.1
Name: numfy
Version: 1.0
Summary: A brief description of your package
Home-page: http://example.com
Author: Your Name
Author-email: your.email@example.com
License: UNKNOWN
Keywords: numfy
Platform: UNKNOWN
Classifier: Development Status :: 3 - Alpha
Classifier: License :: OSI Approved :: MIT License
Classifier: Programming Language :: Python :: 3.6
Classifier: Topic :: Text Processing :: Linguistic
